modreg/__init__.py
modreg/py.typed
modreg/registry.py
modreg-0.1.1.dist-info/METADATA
modreg-0.1.1.dist-info/WHEEL
modreg-0.1.1.dist-info/licenses/LICENSE
modreg-0.1.1.dist-info/RECORD
